openapi_client/__init__.py
openapi_client/api_client.py
openapi_client/configuration.py
openapi_client/exceptions.py
openapi_client/rest.py
openapi_client/api/__init__.py
openapi_client/api/backup_restore_v1_api.py
openapi_client/api/backup_v1_api.py
openapi_client/api/config_dc_upload_call_v1_api.py
openapi_client/api/config_v1_api.py
openapi_client/api/cron_job_config_v1_api.py
openapi_client/api/cron_update_config_v1_api.py
openapi_client/api/database_detail_v1_api.py
openapi_client/api/database_hibernate_v1_api.py
openapi_client/api/database_rescale_v1_api.py
openapi_client/api/database_resize_v1_api.py
openapi_client/api/database_revive_v1_api.py
openapi_client/api/database_upgrade_v1_api.py
openapi_client/api/database_v1_api.py
openapi_client/api/dc_graph_billing_summary_total_v1_api.py
openapi_client/api/dc_graph_billing_summary_v1_api.py
openapi_client/api/dc_graph_cpu_per_hour_by_node_v1_api.py
openapi_client/api/dc_graph_depot_utilization_v1_api.py
openapi_client/api/dc_graph_get_report_all_usage_by_time_range_v1_api.py
openapi_client/api/dc_graph_get_report_billing_summary_v1_api.py
openapi_client/api/dc_graph_get_report_billing_total_per_db_summary_v1_api.py
openapi_client/api/dc_graph_get_report_billing_total_summary_v1_api.py
openapi_client/api/dc_graph_get_report_cpu_per_hour_by_node_v1_api.py
openapi_client/api/dc_graph_get_report_depot_utilization_v1_api.py
openapi_client/api/dc_graph_get_report_memory_usage_v1_api.py
openapi_client/api/dc_graph_get_report_query_per_hour_v1_api.py
openapi_client/api/dc_graph_get_report_query_response_distribution_v1_api.py
openapi_client/api/dc_graph_get_report_total_queries_per_hr_v1_api.py
openapi_client/api/dc_graph_get_report_usage_by_time_range_v1_api.py
openapi_client/api/dc_graph_memory_usage_v1_api.py
openapi_client/api/dc_graph_query_per_hour_v1_api.py
openapi_client/api/dc_graph_query_response_distribution_v1_api.py
openapi_client/api/dc_graph_total_queries_per_hr_v1_api.py
vertica_accelerator_cli-0.0.3.dist-info/LICENSE
vertica_accelerator_cli-0.0.3.dist-info/METADATA
vertica_accelerator_cli-0.0.3.dist-info/WHEEL
vertica_accelerator_cli-0.0.3.dist-info/entry_points.txt
vertica_accelerator_cli-0.0.3.dist-info/top_level.txt
vertica_accelerator_cli-0.0.3.dist-info/RECORD
