Metadata-Version: 2.1
Name: vertica-accelerator-cli
Version: 0.0.3
Summary: Vertica Command Line Interface
Home-page: https://github.com/vertica/vertica-accelerator-cli
Author: XJ, Hao Yang, Kirtan Chavda
Author-email: xj.he@microfocus.com, hao.yang@microfocus.com, kirtan.chavda@microfocus.com
License: (c) Copyright 2021 Micro Focus or one of its affiliates.
Project-URL: Source Code Repo, https://github.com/vertica/vertica-accelerator-cli
Platform: UNKNOWN
Classifier: License :: OSI Approved :: Apache Software License
Classifier: Programming Language :: Python
Classifier: Programming Language :: Python :: 3
Classifier: Programming Language :: Python :: 3.7
Classifier: Programming Language :: Python :: Implementation :: CPython
Classifier: Programming Language :: Python :: Implementation :: PyPy
Requires-Python: >=3.7
License-File: LICENSE
Requires-Dist: setuptools-rust (==0.12.1)
Requires-Dist: pkce (==1.0.3)
Requires-Dist: requests (==2.24.0)
Requires-Dist: environs (==9.3.4)
Requires-Dist: argcomplete (==1.12.3)
Requires-Dist: python-dateutil (==2.8.2)
Requires-Dist: six (==1.16.0)
Requires-Dist: pytest (==6.2.5)
